{
    "1":   "сервер уже запущен. Повторный запуск невозможен",
    "2":   "сервер уже остановлен. Остановка невозможна",
    "3":   "неправильная версия клиента",
    "4":   "пользователь уже подключен к серверу",
    "5":   "пользователь с UIN %s не зарегистрирован",
    "6":   "неверный пароль пользователя UIN %UIN",
    "7":   "пользователь UIN %s заблокирован",
    "8":   "IP адрес \"%s\" заблокирован",
    "9":   "MAC адрес \"%s\" заблокирован",
    "10":  "такой UIN занят",
    "11":  "пользователь с таким UIN не в онлайн или неправильный UIN",
    "12":  "робот не любит ненужного внимания >:[",
    "13":  "конференция с таким UID (%s) не существует",
    "14":  "пользователя UIN: %s нет в конференции UID: %s. Отправка сообщения невозможна",
    "15":  "пользователь UIN: %s при подключении к текстовой конференции UID: %s указал неверный пароль (\"%s\")",
    "16":  "пользователь UIN: %s уже находится в текстовой конференции UID: %s (\"%s\")",
    "17":  "пользователь UIN: %s уже подключен к серверу",
    "18":  "у пользователя UIN: %s недостаточно прав для подключения к серверу",
    "19":  "у пользователя UIN: %s недостаточно прав для размещения сообщения на доске объявлений",
    "20":  "у пользователя UIN: %s недостаточно прав для просмотра доски объявлений",
    "21":  "у пользователя UIN: %s недостаточно прав для создания текстовой конференции",
    "22":  "у пользователя UIN: %s недостаточно прав для подключения к текстовой конференции %s",
    "23":  "у пользователя UIN: %s недостаточно прав для открытия сеанса привата",
    "24":  "у пользователя UIN: %s недостаточно прав для отправки сообщения в текстовую конференцию",
    "25":  "у пользователя UIN: %s недостаточно прав для получения приватного сообщения",
    "26":  "у пользователя UIN: %s недостаточно прав для изменения личных данных",
    "27":  "пользователь UIN: %s не смог создать новую группу контактов \"%s\" - найден дубликат",
    "28":  "пользователь UIN: %s не смог переименовать группу - исходной группы не существует",
    "29":  "пользователь UIN: %s не смог переименовать группу - результирующей группы не существует",
    "30":  "пользователь UIN: %s не смог добавить новый контакт себе в контакт-лист. UIN: %s не существует",
    "31":  "пользователь UIN: %s не смог добавить новый контакт себе в контакт-лист. UIN: %s уже в его контакт-листе",
    "32":  "пользователь UIN: %s не смог добавить новый контакт себе в контакт-лист. Нельзя добавлять самого себя",
    "33":  "пользователь не смог зарегистрировать ник \"%s\" - запрещено дублирование ников",
    "34":  "у пользователя UIN: %s недостаточно прав для изменения своего пароля",
    "35":  "пользователю отказано в регистрации - недопустимый ник",
    "36":  "регистрация новых пользователей запрещена",
    "37":  "UIN должен быть числом > 0",
    "38":  "этот IP адрес (\"%s\") уже заблокирован",
    "39":  "этот MAC адрес (\"%s\") уже заблокирован",
    "40":  "такого IP адреса (\"%s\") нет в блокировках",
    "41":  "такого MAC адреса (\"%s\") нет в блокировках",
    "42":  "пользователь UIN: %s не смог войти в текстовую конференцию \"%s\" - установлен бан на вход",
    "43":  "пользователь UIN: %s не смог отправить сообщение в текстовую конференцию \"%s\" - установлен бан на отправку сообщений в эту конференцию",
    "44":  "пользователь UIN: %s не может отключить от сервера самого себя",
    "45":  "у пользователя UIN: %s недостаточно прав для отключения других пользователей от сервера",
    "46":  "у пользователя UIN: %s недостаточно прав для блокировки IP адресов",
    "47":  "пользователь UIN: %s не может заблокировать свой собственный IP",
    "48":  "у пользователя UIN: %s недостаточно прав для блокировки MAC адресов",
    "49":  "пользователь UIN: %s не может заблокировать свой собственный MAC",
    "50":  "у пользователя UIN: %s недостаточно прав для бана других пользователей",
    "51":  "пользователь UIN: %s не может забанить самого себя",
    "52":  "у пользователя UIN: %s недостаточно прав для того, чтобы выгонять из конференций других пользователей",
    "53":  "пользователя UIN: %s нет в конференции UID: %s",
    "54":  "у пользователя UIN: %s недостаточно прав для установки новой темы в конференции UID: %s",
    "55":  "невозможно запустить сервер. IP адрес указан неправильно либо порт занят другим приложением (WINSOCK error %s)",
    "56":  "невозможно запустить встроенный FTP сервер. IP адрес указан неправильно либо порт занят другим приложением (порт %s, IP %s, DMZ IP %s)",
    "57":  "\"горячая\" клавиша не зарегистрирована - сочетание занято другой программой",
    "58":  "невозможно запустить встроенный FTP сервер: публичная папка \"%s\" не существует или недоступна",
    "59":  "у пользователя UIN: %s недостаточно прав для администрирования сервера через консоль",
    "60":  "такое стоп-слово уже есть в списке",
    "61":  "бана с таким индексом не существует",
    "62":  "у пользователя UIN: %s недостаточно прав для очистки текстовой конференции",
    "63":  "регистрируемый ник находится в списке зарезервированных (\"%s\")",
    "64":  "невозможно создать конференцию, так как название находится в списке блокировок (\"%s\")",
    "65":  "такого стоп-слова нет в списке",
    "66":  "неверный UID конференции",
    "67":  "конференции с таким UID не существует",
    "68":  "сообщение пользователя UIN: %s заблокировано антифлуд-фильтром",
    "69":  "у пользователя UIN: %s нет статуса оператора конференции \"%s\" для изменения темы",
    "70":  "у пользователя UIN: %s недостаточно прав для изменения своего списка контактов",
    "71":  "группа с ID: %s пуста или не существует",
    "72":  "некорректный пакет от клиента UIN: %s. Клиент будет отключен",
    "73":  "невозможно создать конференцию, так как название заблокировано фильтром нецензурных выражений (\"%s\")",
    "74":  "невозможно создать конференцию, так как тема конференции заблокирована фильтром нецензурных выражений (\"%s\")",
    "75":  "недопустимый ник (или ФИО). Название заблокировано фильтром нецензурных выражений (\"%s\")",
    "76":  "IP адрес \"%s\" не входит в список разрешённых IP адресов",
    "77":  "у пользователя UIN: %s недостаточно прав для отправки файлов",
    "78":  "у пользователя UIN: %s недостаточно прав для приёма файлов",
    "79":  "IP %s%s, доменный пользователь \"%s\" не зарегистрирован на сервере",
    "80":  "у пользователя UIN: %s недостаточно прав для отправки персонального сообщения в текстовую конференцию",
    "81":  "у пользователя UIN: %s недостаточно прав для отправки алерт сообщения в текстовую конференцию",
    "82":  "неверный пароль для подключения к серверу с компьютера \"%s\"",
    "83":  "невозможно зарегистрировать нового пользователя - в бесплатной версии MyChat нельзя регистрировать более 50 пользователей",
    "84":  "превышен лимит регистраций с одного MAC адреса (\"%s\")",
    "85":  "сетевая ошибка (WINSOCK %s) %s",
    "86":  "исчерпано максимальное количество соединений на сервере, IP %s",
    "87":  "",
    "88":  "процесс автоматического восстановления базы данных прерван пользователем!",
    "89":  "",
    "90":  "",
    "91":  "",
    "92":  "",
    "93":  "",
    "94":  "",
    "95":  "",
    "96":  "",
    "97":  "",
    "98":  "",
    "99":  "",
    "100": "сетевая ошибка IP %s: %s",
    "101": "неверный пароль при подключении доменного пользователя \"%s\"",
    "102": "попытка подключения неизвестного приложения, IP \"%s\"",
    "103": "ошибка сжатия базы данных!",
    "104": "HardwareID \"%s\" компьютера (IP %s, MAC %s) заблокирован",
    "105": "не удалось создать файл резервной копии базы данных %s. Неверный путь или нет места на жёстком диске",
    "106": "подключение клиента более новой (%s) версии, чем у сервера (%s)",
    "107": "подключение клиента несовместимой версии (%s)",
    "108": "попытка подключения под обычной учётной записью для доменного пользователя (IP %s, MAC %s)",
    "109": "такого пользователя не существует на сервере (IP %s, MAC %s)",
    "110": "пользователь UIN: %s отключен от сервера",
    "111": "невозможно запустить встроенный WEB сервер. Порт %s занят другим приложением",
    "112": "у пользователя UIN: %s недостаточно прав для совершения аудио/видео звонков",
    "113": "не удалось создать файл резервной копии базы данных. %s",
    "114": "пользователь UIN %s не дал разрешения на просмотр своих личных файлов другим пользователям",
    "115": "",
    "116": "не удалось запустить NodeJS Server",
    "117": "нет соединения с NodeJS Server, TCP port: %s",
    "118": "функция WEB-поддержки отключена, IP:%s",
    "119": "функция MyChat Guest отключена",
    "120": "NodeJS Server был аварийно выгружен из памяти",
    "121": "попытка подключения клиента без использования шифрования, IP %s",
    "122": "SSPI ошибка авторизации доменного пользователя IP %s, \"%s\"",
    "123": "ошибка запуска NodeJS (Exit сode = %s)",
    "124": "попытка подключения старой версии приложения (ниже 4.7)",
    "125": "попытка подключения старой версии приложения (ниже 5.0), IP %s",
    "126": "у пользователя UIN: %s недостаточно прав для доступа к Kanban",
    "127": "пользователь UIN %s не может ответить на звонок пользователя UIN %s, потому что сейчас разговаривает с другим человеком",
    "128": "служба \"MyChatTurnServer\" не установлена",
    "129": "у пользователя UIN : %s недостаточно прав для администрирования сервера",
    "130": "скрипт \"%s\" отключен из-за превышения времени на выполнение (%s ms)",
    "131": "неверно указан тип аутентификации пользователя, IP %s",
    "132": "у пользователя UIN: %s недостаточно прав для доступа к форуму",
    "133": "у пользователя UIN: %s недостаточно прав создания разделов в форуме",
    "134": "ошибка при добавлении нового раздела в форум пользователем UIN: %s. Неправильный ParentID (%s)",
    "135": "ошибка при добавлении нового раздела в форум пользователем UIN: %s. Название не может быть пустым",
    "136": "у пользователя UIN: %s недостаточно прав для изменения разделов форума",
    "137": "ошибка изменения раздела в форуме пользователем UIN: %s. Неправильный ParentID (%s)",
    "138": "ошибка при изменении раздела в форуме пользователем UIN: %s. Название не может быть пустым",
    "139": "у пользователя UIN: %s недостаточно прав создания тем в форуме",
    "140": "ошибка при добавлении новой темы в форум пользователем UIN: %s. Неправильный ParentID (%s)",
    "141": "ошибка при добавлении новой темы в форум пользователем UIN: %s. Название не может быть пустым",
    "142": "у пользователя UIN: %s недостаточно прав для изменения тем в форуме",
    "143": "ошибка изменения темы в форуме пользователем UIN: %s. Неправильный ParentID (%s)",
    "144": "ошибка при изменении темы в форуме пользователем UIN: %s. Название не может быть пустым",
    "145": "у пользователя UIN: %s недостаточно прав для создания сообщений в форуме",
    "146": "ошибка при добавлении нового сообщения в форум пользователем UIN: %s. Неправильный ParentID (%s)",
    "147": "ошибка при добавлении нового сообщения в форум пользователем UIN: %s. Название не может быть пустым",
    "148": "у пользователя UIN: %s недостаточно прав для изменения сообщений в форуме",
    "149": "ошибка при удалении сообщения на форуме пользователем UIN: %s. Неправильный ID (%s)",
    "150": "ошибка при удалении темы в форуме пользователем UIN: %s. Несуществующий ID (%s)",
    "151": "ошибка при изменении сообщения на форуме пользователем UIN: %s. Неправильный ParentID (%s)",
    "152": "ошибка при изменении сообщения на форуме пользователем UIN: %s. Название не может быть пустым",
    "153": "ошибка изменения сообщения на форуме пользователем UIN: %s. Неправильный ID (%s)",
    "154": "ошибка при удалении раздела в форуме пользователем UIN: %s. Несуществующий ID (%s)",
    "155": "у пользователя UIN: %s недостаточно прав для изменения собственных сообщений в форуме",
    "156": "у пользователя UIN: %s недостаточно прав для удаления секций в форуме",
    "157": "у пользователя UIN: %s недостаточно прав для удаления тем в форуме",
    "158": "у пользователя UIN: %s недостаточно прав для удаления сообщений в форуме",
    "159": "у пользователя UIN: %s недостаточно прав для удаления собственных сообщений в форуме",
    "160": "NodeJS HTTPS ошибка: %s",
    "161": "ошибка авторизации, неверный токен (App %s, IP %s)",
    "162": "ошибка авторизации, неверный тип приложения для токена (App %s, IP %s)",
    "163": "превышен лимит регистраций с одного HardwareID адреса (IP %s, HardwareID \"%s\")",
    "164": "превышен лимит регистраций с одного IP адреса (IP %s)"
}